odoo/addons/shopinvader_delivery_state/README.rst
odoo/addons/shopinvader_delivery_state/__init__.py
odoo/addons/shopinvader_delivery_state/__manifest__.py
odoo/addons/shopinvader_delivery_state/hooks.py
odoo/addons/shopinvader_delivery_state/i18n/shopinvader_delivery_state.pot
odoo/addons/shopinvader_delivery_state/models/__init__.py
odoo/addons/shopinvader_delivery_state/models/sale_order.py
odoo/addons/shopinvader_delivery_state/readme/CONTRIBUTORS.rst
odoo/addons/shopinvader_delivery_state/readme/CREDITS.rst
odoo/addons/shopinvader_delivery_state/readme/DESCRIPTION.rst
odoo/addons/shopinvader_delivery_state/static/description/index.html
odoo/addons/shopinvader_delivery_state/tests/__init__.py
odoo/addons/shopinvader_delivery_state/tests/test_sale.py
odoo_addon_shopinvader_delivery_state-16.0.1.0.1.dist-info/METADATA
odoo_addon_shopinvader_delivery_state-16.0.1.0.1.dist-info/WHEEL
odoo_addon_shopinvader_delivery_state-16.0.1.0.1.dist-info/top_level.txt
odoo_addon_shopinvader_delivery_state-16.0.1.0.1.dist-info/RECORD
